{"title":"Lab 13: <br> Open Materials","markdown":{"yaml":{"title":"Lab 13: <br> Open Materials","subtitle":"Goal: 100% Replicability","author":[{"name":"Dr. Gordon Wright","orcid":"0000-0001-9424-5743","email":"g.wright@gold.ac.uk"}],"date":"01/23/2023","date-format":"long","license":"CC BY-NC-SA","citations-hover":true,"categories":["Lab","Week Template"],"format":{"revealjs":{"title-slide-attributes":{"data-background-color":"#6667ab"},"header-logo":"/images/rmmonkey.png","header":"Research Methods Lab 13 - Open Materials","hide-from-titleSlide":"text","slide-number":"c/t"}},"filters":["reveal-header"],"execute":{"echo":false,"freeze":"auto"},"embed-resources":true},"headingText":"Overview of today's lab activities","containsRefs":false,"markdown":"\n\n\n1.  Keep on collecting data\n\n2.  Understand the Submission Requirements for your Mini-Dissertation\n\n3.  Start considering what goes in to your Mini-Dissertation\n\n## Data Collection\n\nPlease take part in the Study Swap and email Gordon with any new studies\ncoming online\n\n## See what a Mini-Dissertation submission looks like\n\n1 - The Mini-Diss itself\n\n2 - Open Data (e.g. Excel)\n\n3 - Open Materials (e.g. pdf)\n\n![](/content/MiniDissWriting/images/O6.png)\n\n## Review the Mini-Dissertation Writing Guide ch03 - Open Materials\n\nYou are able to start assembling the Open Materials (as well as writing\nyour Method section) as soon as you have ethical approval!\n","srcMarkdownNoYaml":"\n\n# Overview of today's lab activities\n\n1.  Keep on collecting data\n\n2.  Understand the Submission Requirements for your Mini-Dissertation\n\n3.  Start considering what goes in to your Mini-Dissertation\n\n## Data Collection\n\nPlease take part in the Study Swap and email Gordon with any new studies\ncoming online\n\n## See what a Mini-Dissertation submission looks like\n\n1 - The Mini-Diss itself\n\n2 - Open Data (e.g. Excel)\n\n3 - Open Materials (e.g. pdf)\n\n![](/content/MiniDissWriting/images/O6.png)\n\n## Review the Mini-Dissertation Writing Guide ch03 - Open Materials\n\nYou are able to start assembling the Open Materials (as well as writing\nyour Method section) as soon as you have ethical approval!\n"},"formats":{"revealjs":{"identifier":{"display-name":"RevealJS","target-format":"revealjs","base-format":"revealjs"},"execute":{"fig-width":10,"fig-height":5,"fig-format":"retina","fig-dpi":96,"df-print":"default","error":false,"eval":true,"cache":null,"freeze":"auto","echo":false,"output":true,"warning":false,"include":true,"keep-md":false,"keep-ipynb":false,"ipynb":null,"enabled":null,"daemon":null,"daemon-restart":false,"debug":false,"ipynb-filters":[],"ipynb-shell-interactivity":null,"plotly-connected":true,"engine":"markdown"},"render":{"keep-tex":false,"keep-typ":false,"keep-source":false,"keep-hidden":false,"prefer-html":false,"output-divs":true,"output-ext":"slides.html","fig-align":"default","fig-pos":null,"fig-env":null,"code-fold":"none","code-overflow":"scroll","code-link":false,"code-line-numbers":true,"code-tools":false,"tbl-colwidths":"auto","merge-includes":true,"inline-includes":false,"preserve-yaml":false,"latex-auto-mk":true,"latex-auto-install":true,"latex-clean":true,"latex-min-runs":1,"latex-max-runs":10,"latex-makeindex":"makeindex","latex-makeindex-opts":[],"latex-tlmgr-opts":[],"latex-input-paths":[],"latex-output-dir":null,"link-external-icon":false,"link-external-newwindow":false,"self-contained-math":false,"format-resources":[]},"pandoc":{"standalone":true,"wrap":"none","default-image-extension":"png","html-math-method":{"method":"mathjax","url":"https://cdnjs.cloudflare.com/ajax/libs/mathjax/2.7.0/MathJax.js?config=TeX-AMS_HTML-full"},"slide-level":2,"to":"revealjs","citeproc":true,"filters":["reveal-header","fontawesome"],"embed-resources":true,"output-file":"lab.slides.html"},"language":{"toc-title-document":"Table of contents","toc-title-website":"On this page","related-formats-title":"Other Formats","related-notebooks-title":"Notebooks","source-notebooks-prefix":"Source","other-links-title":"Other Links","code-links-title":"Code Links","launch-dev-container-title":"Launch Dev Container","launch-binder-title":"Launch Binder","article-notebook-label":"Article Notebook","notebook-preview-download":"Download Notebook","notebook-preview-download-src":"Download Source","notebook-preview-back":"Back to Article","manuscript-meca-bundle":"MECA Bundle","section-title-abstract":"Abstract","section-title-appendices":"Appendices","section-title-footnotes":"Footnotes","section-title-references":"References","section-title-reuse":"Reuse","section-title-copyright":"Copyright","section-title-citation":"Citation","appendix-attribution-cite-as":"For attribution, please cite this work as:","appendix-attribution-bibtex":"BibTeX citation:","title-block-author-single":"Author","title-block-author-plural":"Authors","title-block-affiliation-single":"Affiliation","title-block-affiliation-plural":"Affiliations","title-block-published":"Published","title-block-modified":"Modified","title-block-keywords":"Keywords","callout-tip-title":"Tip","callout-note-title":"Note","callout-warning-title":"Warning","callout-important-title":"Important","callout-caution-title":"Caution","code-summary":"Code","code-tools-menu-caption":"Code","code-tools-show-all-code":"Show All Code","code-tools-hide-all-code":"Hide All Code","code-tools-view-source":"View Source","code-tools-source-code":"Source Code","code-line":"Line","code-lines":"Lines","copy-button-tooltip":"Copy to Clipboard","copy-button-tooltip-success":"Copied!","repo-action-links-edit":"Edit this page","repo-action-links-source":"View source","repo-action-links-issue":"Report an issue","back-to-top":"Back to top","search-no-results-text":"No results","search-matching-documents-text":"matching documents","search-copy-link-title":"Copy link to search","search-hide-matches-text":"Hide additional matches","search-more-match-text":"more match in this document","search-more-matches-text":"more matches in this document","search-clear-button-title":"Clear","search-text-placeholder":"","search-detached-cancel-button-title":"Cancel","search-submit-button-title":"Submit","search-label":"Search","toggle-section":"Toggle section","toggle-sidebar":"Toggle sidebar navigation","toggle-dark-mode":"Toggle dark mode","toggle-reader-mode":"Toggle reader mode","toggle-navigation":"Toggle navigation","crossref-fig-title":"Figure","crossref-tbl-title":"Table","crossref-lst-title":"Listing","crossref-thm-title":"Theorem","crossref-lem-title":"Lemma","crossref-cor-title":"Corollary","crossref-prp-title":"Proposition","crossref-cnj-title":"Conjecture","crossref-def-title":"Definition","crossref-exm-title":"Example","crossref-exr-title":"Exercise","crossref-ch-prefix":"Chapter","crossref-apx-prefix":"Appendix","crossref-sec-prefix":"Section","crossref-eq-prefix":"Equation","crossref-lof-title":"List of Figures","crossref-lot-title":"List of Tables","crossref-lol-title":"List of Listings","environment-proof-title":"Proof","environment-remark-title":"Remark","environment-solution-title":"Solution","listing-page-order-by":"Order By","listing-page-order-by-default":"Default","listing-page-order-by-date-asc":"Oldest","listing-page-order-by-date-desc":"Newest","listing-page-order-by-number-desc":"High to Low","listing-page-order-by-number-asc":"Low to High","listing-page-field-date":"Date","listing-page-field-title":"Title","listing-page-field-description":"Description","listing-page-field-author":"Author","listing-page-field-filename":"File Name","listing-page-field-filemodified":"Modified","listing-page-field-subtitle":"Subtitle","listing-page-field-readingtime":"Reading Time","listing-page-field-wordcount":"Word Count","listing-page-field-categories":"Categories","listing-page-minutes-compact":"{0} min","listing-page-category-all":"All","listing-page-no-matches":"No matching items","listing-page-words":"{0} words"},"metadata":{"lang":"en","fig-responsive":false,"quarto-version":"1.4.533","auto-stretch":true,"modulecode":"PS52007D","bibliography":["../../references.bib","../../textbook.bib"],"csl":"../../apa7.csl","date-format":"long","_quarto-vars":{"author":"Gordon Wright","email":"g.wright@gold.ac.uk","instructor":{"name":"Dr. Gordon Wright","name_no_title":"Gordon Wright","email":"g.wright@gold.ac.uk","url":"www.littlemonkeylab.com","twitter":"drdeception","github":"LittleMonkeyLab","office":"Whitehead 200/1","contact_policy":"E-mail is the best ways to get in contact with me. I will try to respond to all course-related e-mails within 24 hours. Any questions relating to the course, coursework or anything not personal/confidential in nature should be submitted to the Course Forum. This benefits all students. So, if you email me about the course, don't be surprised if you get a brief 'Please post this to the Forum' message!   Office hours are advertised on the module VLE page."},"course":{"number":"PS52007D","semester":"Academic Year 2023-4","days":"Monday Lecture | Tuesday Labs","time":"10am","location":"PSH LG02","dates":"October to March, 2023-4","github":"https://www.github.com/littlemonkeylab/PS52007D_2023-4","url":"https://littlemonkeylab.com/PS52007D_2023-4","copyright_year":"2023"},"university":{"name":"Goldsmiths, University of London","url":"https://www.gold.ac.uk"},"school":{"name":"Department of Psychology","url":"https://gold.ac.uk/psychology"}},"comments":{"hypothesis":{"theme":"clean","openSidebar":false}},"editor":"visual","theme":"../_resources/templates/lectures.scss","mainfont":"Atkinson Hyperlegible","slideNumber":"c/t","menu":true,"controls":true,"navigationMode":"linear","controlsLayout":"edges","showSlideNumber":"all","previewLinks":true,"margin":0.2,"smaller":false,"pdfPageHeightOffset":-2,"max-width":"90%","maxScale":2,"pdfMaxPagesPerSlide":1,"title":"Lab 13: <br> Open Materials","subtitle":"Goal: 100% Replicability","author":[{"name":"Dr. Gordon Wright","orcid":"0000-0001-9424-5743","email":"g.wright@gold.ac.uk"}],"date":"01/23/2023","license":"CC BY-NC-SA","citations-hover":true,"categories":["Lab","Week Template"],"title-slide-attributes":{"data-background-color":"#6667ab"},"header-logo":"/images/rmmonkey.png","header":"Research Methods Lab 13 - Open Materials","hide-from-titleSlide":"text"}},"pptx":{"identifier":{"display-name":"Powerpoint","target-format":"pptx","base-format":"pptx"},"execute":{"fig-width":11,"fig-height":5.5,"fig-format":"png","fig-dpi":96,"df-print":"default","error":false,"eval":true,"cache":null,"freeze":"auto","echo":false,"output":true,"warning":false,"include":true,"keep-md":false,"keep-ipynb":false,"ipynb":null,"enabled":null,"daemon":null,"daemon-restart":false,"debug":false,"ipynb-filters":[],"ipynb-shell-interactivity":null,"plotly-connected":true,"engine":"markdown"},"render":{"keep-tex":false,"keep-typ":false,"keep-source":false,"keep-hidden":false,"prefer-html":false,"output-divs":false,"output-ext":"pptx","fig-align":"default","fig-pos":null,"fig-env":null,"code-fold":"none","code-overflow":"scroll","code-link":false,"code-line-numbers":false,"code-tools":false,"tbl-colwidths":true,"merge-includes":true,"inline-includes":false,"preserve-yaml":false,"latex-auto-mk":true,"latex-auto-install":true,"latex-clean":true,"latex-min-runs":1,"latex-max-runs":10,"latex-makeindex":"makeindex","latex-makeindex-opts":[],"latex-tlmgr-opts":[],"latex-input-paths":[],"latex-output-dir":null,"link-external-icon":false,"link-external-newwindow":false,"self-contained-math":false,"format-resources":[],"page-width":10},"pandoc":{"default-image-extension":"png","to":"pptx","citeproc":true,"reference-doc":"../_resources/templates/pptx/RMLecturepptxTemplate.pptx","filters":["reveal-header"],"embed-resources":true,"output-file":"lab.pptx"},"language":{"toc-title-document":"Table of contents","toc-title-website":"On this page","related-formats-title":"Other Formats","related-notebooks-title":"Notebooks","source-notebooks-prefix":"Source","other-links-title":"Other Links","code-links-title":"Code Links","launch-dev-container-title":"Launch Dev Container","launch-binder-title":"Launch Binder","article-notebook-label":"Article Notebook","notebook-preview-download":"Download Notebook","notebook-preview-download-src":"Download Source","notebook-preview-back":"Back to Article","manuscript-meca-bundle":"MECA Bundle","section-title-abstract":"Abstract","section-title-appendices":"Appendices","section-title-footnotes":"Footnotes","section-title-references":"References","section-title-reuse":"Reuse","section-title-copyright":"Copyright","section-title-citation":"Citation","appendix-attribution-cite-as":"For attribution, please cite this work as:","appendix-attribution-bibtex":"BibTeX citation:","title-block-author-single":"Author","title-block-author-plural":"Authors","title-block-affiliation-single":"Affiliation","title-block-affiliation-plural":"Affiliations","title-block-published":"Published","title-block-modified":"Modified","title-block-keywords":"Keywords","callout-tip-title":"Tip","callout-note-title":"Note","callout-warning-title":"Warning","callout-important-title":"Important","callout-caution-title":"Caution","code-summary":"Code","code-tools-menu-caption":"Code","code-tools-show-all-code":"Show All Code","code-tools-hide-all-code":"Hide All Code","code-tools-view-source":"View Source","code-tools-source-code":"Source Code","code-line":"Line","code-lines":"Lines","copy-button-tooltip":"Copy to Clipboard","copy-button-tooltip-success":"Copied!","repo-action-links-edit":"Edit this page","repo-action-links-source":"View source","repo-action-links-issue":"Report an issue","back-to-top":"Back to top","search-no-results-text":"No results","search-matching-documents-text":"matching documents","search-copy-link-title":"Copy link to search","search-hide-matches-text":"Hide additional matches","search-more-match-text":"more match in this document","search-more-matches-text":"more matches in this document","search-clear-button-title":"Clear","search-text-placeholder":"","search-detached-cancel-button-title":"Cancel","search-submit-button-title":"Submit","search-label":"Search","toggle-section":"Toggle section","toggle-sidebar":"Toggle sidebar navigation","toggle-dark-mode":"Toggle dark mode","toggle-reader-mode":"Toggle reader mode","toggle-navigation":"Toggle navigation","crossref-fig-title":"Figure","crossref-tbl-title":"Table","crossref-lst-title":"Listing","crossref-thm-title":"Theorem","crossref-lem-title":"Lemma","crossref-cor-title":"Corollary","crossref-prp-title":"Proposition","crossref-cnj-title":"Conjecture","crossref-def-title":"Definition","crossref-exm-title":"Example","crossref-exr-title":"Exercise","crossref-ch-prefix":"Chapter","crossref-apx-prefix":"Appendix","crossref-sec-prefix":"Section","crossref-eq-prefix":"Equation","crossref-lof-title":"List of Figures","crossref-lot-title":"List of Tables","crossref-lol-title":"List of Listings","environment-proof-title":"Proof","environment-remark-title":"Remark","environment-solution-title":"Solution","listing-page-order-by":"Order By","listing-page-order-by-default":"Default","listing-page-order-by-date-asc":"Oldest","listing-page-order-by-date-desc":"Newest","listing-page-order-by-number-desc":"High to Low","listing-page-order-by-number-asc":"Low to High","listing-page-field-date":"Date","listing-page-field-title":"Title","listing-page-field-description":"Description","listing-page-field-author":"Author","listing-page-field-filename":"File Name","listing-page-field-filemodified":"Modified","listing-page-field-subtitle":"Subtitle","listing-page-field-readingtime":"Reading Time","listing-page-field-wordcount":"Word Count","listing-page-field-categories":"Categories","listing-page-minutes-compact":"{0} min","listing-page-category-all":"All","listing-page-no-matches":"No matching items","listing-page-words":"{0} words"},"metadata":{"modulecode":"PS52007D","bibliography":["../../references.bib","../../textbook.bib"],"csl":"../../apa7.csl","date-format":"long","_quarto-vars":{"author":"Gordon Wright","email":"g.wright@gold.ac.uk","instructor":{"name":"Dr. Gordon Wright","name_no_title":"Gordon Wright","email":"g.wright@gold.ac.uk","url":"www.littlemonkeylab.com","twitter":"drdeception","github":"LittleMonkeyLab","office":"Whitehead 200/1","contact_policy":"E-mail is the best ways to get in contact with me. I will try to respond to all course-related e-mails within 24 hours. Any questions relating to the course, coursework or anything not personal/confidential in nature should be submitted to the Course Forum. This benefits all students. So, if you email me about the course, don't be surprised if you get a brief 'Please post this to the Forum' message!   Office hours are advertised on the module VLE page."},"course":{"number":"PS52007D","semester":"Academic Year 2023-4","days":"Monday Lecture | Tuesday Labs","time":"10am","location":"PSH LG02","dates":"October to March, 2023-4","github":"https://www.github.com/littlemonkeylab/PS52007D_2023-4","url":"https://littlemonkeylab.com/PS52007D_2023-4","copyright_year":"2023"},"university":{"name":"Goldsmiths, University of London","url":"https://www.gold.ac.uk"},"school":{"name":"Department of Psychology","url":"https://gold.ac.uk/psychology"}},"comments":{"hypothesis":{"theme":"clean","openSidebar":false}},"editor":"visual","title":"Lab 13: <br> Open Materials","subtitle":"Goal: 100% Replicability","author":[{"name":"Dr. Gordon Wright","orcid":"0000-0001-9424-5743","email":"g.wright@gold.ac.uk"}],"date":"01/23/2023","license":"CC BY-NC-SA","citations-hover":true,"categories":["Lab","Week Template"]}},"html":{"identifier":{"display-name":"HTML","target-format":"html","base-format":"html"},"execute":{"fig-width":7,"fig-height":5,"fig-format":"retina","fig-dpi":96,"df-print":"default","error":false,"eval":true,"cache":null,"freeze":"auto","echo":false,"output":true,"warning":true,"include":true,"keep-md":false,"keep-ipynb":false,"ipynb":null,"enabled":null,"daemon":null,"daemon-restart":false,"debug":false,"ipynb-filters":[],"ipynb-shell-interactivity":null,"plotly-connected":true,"engine":"markdown"},"render":{"keep-tex":false,"keep-typ":false,"keep-source":false,"keep-hidden":false,"prefer-html":false,"output-divs":true,"output-ext":"html","fig-align":"default","fig-pos":null,"fig-env":null,"code-fold":true,"code-overflow":"wrap","code-link":false,"code-line-numbers":false,"code-tools":false,"tbl-colwidths":"auto","merge-includes":true,"inline-includes":false,"preserve-yaml":false,"latex-auto-mk":true,"latex-auto-install":true,"latex-clean":true,"latex-min-runs":1,"latex-max-runs":10,"latex-makeindex":"makeindex","latex-makeindex-opts":[],"latex-tlmgr-opts":[],"latex-input-paths":[],"latex-output-dir":null,"link-external-icon":false,"link-external-newwindow":false,"self-contained-math":false,"format-resources":[],"notebook-links":true},"pandoc":{"standalone":true,"wrap":"none","default-image-extension":"png","to":"html","citeproc":true,"toc":true,"embed-resources":true,"css":["../../include/webex.css","../../styles.css"],"include-after-body":["../../include/webex.js"],"filters":["fontawesome","reveal-header"],"output-file":"lab.html"},"language":{"toc-title-document":"Table of contents","toc-title-website":"On this page","related-formats-title":"Other Formats","related-notebooks-title":"Notebooks","source-notebooks-prefix":"Source","other-links-title":"Other Links","code-links-title":"Code Links","launch-dev-container-title":"Launch Dev Container","launch-binder-title":"Launch Binder","article-notebook-label":"Article Notebook","notebook-preview-download":"Download Notebook","notebook-preview-download-src":"Download Source","notebook-preview-back":"Back to Article","manuscript-meca-bundle":"MECA Bundle","section-title-abstract":"Abstract","section-title-appendices":"Appendices","section-title-footnotes":"Footnotes","section-title-references":"References","section-title-reuse":"Reuse","section-title-copyright":"Copyright","section-title-citation":"Citation","appendix-attribution-cite-as":"For attribution, please cite this work as:","appendix-attribution-bibtex":"BibTeX citation:","title-block-author-single":"Author","title-block-author-plural":"Authors","title-block-affiliation-single":"Affiliation","title-block-affiliation-plural":"Affiliations","title-block-published":"Published","title-block-modified":"Modified","title-block-keywords":"Keywords","callout-tip-title":"Tip","callout-note-title":"Note","callout-warning-title":"Warning","callout-important-title":"Important","callout-caution-title":"Caution","code-summary":"Code","code-tools-menu-caption":"Code","code-tools-show-all-code":"Show All Code","code-tools-hide-all-code":"Hide All Code","code-tools-view-source":"View Source","code-tools-source-code":"Source Code","code-line":"Line","code-lines":"Lines","copy-button-tooltip":"Copy to Clipboard","copy-button-tooltip-success":"Copied!","repo-action-links-edit":"Edit this page","repo-action-links-source":"View source","repo-action-links-issue":"Report an issue","back-to-top":"Back to top","search-no-results-text":"No results","search-matching-documents-text":"matching documents","search-copy-link-title":"Copy link to search","search-hide-matches-text":"Hide additional matches","search-more-match-text":"more match in this document","search-more-matches-text":"more matches in this document","search-clear-button-title":"Clear","search-text-placeholder":"","search-detached-cancel-button-title":"Cancel","search-submit-button-title":"Submit","search-label":"Search","toggle-section":"Toggle section","toggle-sidebar":"Toggle sidebar navigation","toggle-dark-mode":"Toggle dark mode","toggle-reader-mode":"Toggle reader mode","toggle-navigation":"Toggle navigation","crossref-fig-title":"Figure","crossref-tbl-title":"Table","crossref-lst-title":"Listing","crossref-thm-title":"Theorem","crossref-lem-title":"Lemma","crossref-cor-title":"Corollary","crossref-prp-title":"Proposition","crossref-cnj-title":"Conjecture","crossref-def-title":"Definition","crossref-exm-title":"Example","crossref-exr-title":"Exercise","crossref-ch-prefix":"Chapter","crossref-apx-prefix":"Appendix","crossref-sec-prefix":"Section","crossref-eq-prefix":"Equation","crossref-lof-title":"List of Figures","crossref-lot-title":"List of Tables","crossref-lol-title":"List of Listings","environment-proof-title":"Proof","environment-remark-title":"Remark","environment-solution-title":"Solution","listing-page-order-by":"Order By","listing-page-order-by-default":"Default","listing-page-order-by-date-asc":"Oldest","listing-page-order-by-date-desc":"Newest","listing-page-order-by-number-desc":"High to Low","listing-page-order-by-number-asc":"Low to High","listing-page-field-date":"Date","listing-page-field-title":"Title","listing-page-field-description":"Description","listing-page-field-author":"Author","listing-page-field-filename":"File Name","listing-page-field-filemodified":"Modified","listing-page-field-subtitle":"Subtitle","listing-page-field-readingtime":"Reading Time","listing-page-field-wordcount":"Word Count","listing-page-field-categories":"Categories","listing-page-minutes-compact":"{0} min","listing-page-category-all":"All","listing-page-no-matches":"No matching items","listing-page-words":"{0} words"},"metadata":{"lang":"en","fig-responsive":true,"quarto-version":"1.4.533","modulecode":"PS52007D","bibliography":["../../references.bib","../../textbook.bib"],"csl":"../../apa7.csl","date-format":"long","_quarto-vars":{"author":"Gordon Wright","email":"g.wright@gold.ac.uk","instructor":{"name":"Dr. Gordon Wright","name_no_title":"Gordon Wright","email":"g.wright@gold.ac.uk","url":"www.littlemonkeylab.com","twitter":"drdeception","github":"LittleMonkeyLab","office":"Whitehead 200/1","contact_policy":"E-mail is the best ways to get in contact with me. I will try to respond to all course-related e-mails within 24 hours. Any questions relating to the course, coursework or anything not personal/confidential in nature should be submitted to the Course Forum. This benefits all students. So, if you email me about the course, don't be surprised if you get a brief 'Please post this to the Forum' message!   Office hours are advertised on the module VLE page."},"course":{"number":"PS52007D","semester":"Academic Year 2023-4","days":"Monday Lecture | Tuesday Labs","time":"10am","location":"PSH LG02","dates":"October to March, 2023-4","github":"https://www.github.com/littlemonkeylab/PS52007D_2023-4","url":"https://littlemonkeylab.com/PS52007D_2023-4","copyright_year":"2023"},"university":{"name":"Goldsmiths, University of London","url":"https://www.gold.ac.uk"},"school":{"name":"Department of Psychology","url":"https://gold.ac.uk/psychology"}},"comments":{"hypothesis":{"theme":"clean","openSidebar":false}},"theme":"simplex","mainfont":"Atkinson Hyperlegible","monofont":"Fira Code","linkcolor":"#BE3455","grid":{"sidebar-width":"250px","body-width":"900px","margin-width":"300px"},"editor":"visual","title":"Lab 13: <br> Open Materials","subtitle":"Goal: 100% Replicability","author":[{"name":"Dr. Gordon Wright","orcid":"0000-0001-9424-5743","email":"g.wright@gold.ac.uk"}],"date":"01/23/2023","license":"CC BY-NC-SA","citations-hover":true,"categories":["Lab","Week Template"]},"extensions":{"book":{"multiFile":true}}}},"projectFormats":["html","pdf"]}