{
  "hash": "0ca449c7775018f1cc9f5ad7ca0cb6ae",
  "result": {
    "markdown": "---\ntitle: \"Lab 01: <br> Replace it!\"\nsubtitle: \"This is a meaningful subtitle\"\nauthor: \n  - name: \"Dr. Gordon Wright\"\n    orcid: 0000-0001-9424-5743\n    email: g.wright@gold.ac.uk\ndate: \"10/02/2023\"\ndate-format: long\nlicense: \"CC BY-NC-SA\"\nfooter: \"[🔗 VLE](https://www.bbc.co.uk)\"\ncitations-hover: true\ncategories: \n  - \"Lab\"\n  - \"Week 1\"\nparams:\n  class: \"lab01\"\nformat: \n  # pdf: default\n  pptx: default\n  html: default\n  docx: default\n  revealjs: \n    header-logo: \"/images/rmlogo.png\"\n    header: \"Research Methods Lab 01 - Short Title\" # Replace it\n    hide-from-titleSlide: \"text\"\nfilters:\n  - reveal-header\nexecute:\n echo: false\n freeze: auto\nembed-resources: true\n  # Title page populated by content above\n---\n\n::: {.cell}\n\n:::\n\n\n# Show Attendance QR Code\n\n# Heading 1 - Section Head\n\nThis is a subtitle to the section header\n\n## Heading 2 - new slide title\n\nHeading 2 copy\n\n### Heading 3 - italic emphasis\n\n## Spans for text accentuation - available in source mode\n\n[.shout]{.shout} accent3(red) 1.5em and Bold\n\n[.alert]{.alert} accent3(red) no change to font size\n\n[.fg]{.fg} [.bg]{.bg}\n\n[.button]{.button} accent1 whitetext button for link\n\n[.button-success]{.button-success}\n\n[.takeaway]{.takeaway}\n\n[.highlight]{.highlight}\n\n## Citations\n\n@wright2012\n\n@Cohen1992 In text citation `@Cohen1992`\n\n[@Cohen1992] not in-text citation \\`[@Cohen1992]\n\njust type \\`\\@\\` and a search box comes up for your Zotero library or a\n.bib file associated with the project\n\n## Image\\|content 2 column\n\nSlide with image and commentary in two columns and some explanatory text\nabove\n\ntext text text text text text text text text text text text\n\ntext text text text text text text text text text text text\n\n::: columns\n::: {.column width=\"60%\"}\n![](images/TestImage.png)\n:::\n\n::: {.column width=\"40%\"}\nHere is some text\n\n-   Bullet 1\n\n-   Bullet 2\n\n-   Bullet 3\n:::\n:::\n\n## Callouts\n\n## Note Callouts\n\n::: callout-note\n## Note default\n\ncontent\n:::\n\n::: {.callout-note appearance=\"simple\"}\n## Note simple\n\ncontent\n:::\n\n::: {.callout-note appearance=\"minimal\"}\n## Note minimal\n\ncontent\n:::\n\n## Icons by FontAwesome\n\nThese are cool {{< fa user >}} but they do need a full render e.g.\n`$ quarto render` in order to be seen.\n\nThey can also be used in pdfs\n\n| input                             |                output                 |\n|:----------------------------------|:-------------------------------------:|\n| `{{{< fa binoculars >}}}`         |     {{< fa binoculars >}} Prepare     |\n| `{{{< fa chalkboard-teacher >}}}` | {{< fa chalkboard-teacher >}} Lecture |\n| `{{{< fa users >}}}`              |         {{< fa users >}} Lab          |\n| `{{{< fa bookmark >}}}`           |      {{< fa bookmark >}} Reading      |\n| `{{{< fa book >}}}`               |   {{< fa book >}} Mini-Dissertation   |\n\n: Fontawesome {.striped .sm}\n\n## References\n",
    "supporting": [],
    "filters": [
      "rmarkdown/pagebreak.lua"
    ],
    "includes": {},
    "engineDependencies": {},
    "preserve": null,
    "postProcess": false
  }
}