{"title":"Practical Issues 2023: Deviously Seeking Duping Delight in the Dark","markdown":{"yaml":{"title":"Practical Issues 2023: Deviously Seeking Duping Delight in the Dark","subtitle":"LittleMonkeyLab","image":"lecture.png","author":[{"name":"Dr. Gordon Wright","orcid":"0000-0001-9424-5743","email":"g.wright@gold.ac.uk"}],"date":"10/31/2023","date-format":"long","license":"CC BY-NC-SA","citations-hover":true,"categories":["Lecture","Week 21"],"params":{"class":"lec21"},"format":{"pdf":"default","pptx":"default","html":"default","docx":"default","revealjs":{"title-slide-attributes":{"data-background-color":"#BE3455"},"header-logo":"/images/LMLLOGO.png","header":"Practical Issues - Duping Delight","hide-from-titleSlide":"text","slide-number":"c/t"}},"filters":["reveal-header"],"execute":{"echo":false,"freeze":"auto"},"embed-resources":true},"headingText":"Overview","containsRefs":false,"markdown":"\n\n\n. . .\n\n::: {.callout-important appearance=\"minimal\"}\nAs Module Coordinator of Y2 Research Methods - give some forward-looking\nguidance!\n:::\n\n. . .\n\n::: {.callout-caution appearance=\"minimal\"}\nDo the 'Lie of the Land' survey - tap your deception expertise!\n:::\n\n. . .\n\n> BREAK - 10-15 mins\n\n. . .\n\n::: {.callout-important appearance=\"minimal\"}\nA brief overview of my research\n:::\n\n. . .\n\n::: {.callout-tip appearance=\"minimal\"}\nToday's Target Paper\n:::\n\n. . .\n\n::: {.callout-caution appearance=\"minimal\"}\nQuestions *(of which I hear you usually have many!)*\n:::\n\n# *From one Researcher to another... I mean YOU!*\n\n## A brief introduction\n\n::: columns\n::: column\nDr. Gordon Wright\n\nLecturer in Psychology\n\nModule Coordinator - Y2 Research Methods\n\ng.wright\\@gold.ac.uk\n:::\n:::\n\n## But who are you?\n\n. . .\n\n\\\nWhat do I need to know?\n\n. . .\n\n\\\nWhy did you choose to study at Goldsmiths?\n\n. . .\n\n\\\nWhy Psychology?\n\n## Why does that matter this year?\n\n. . .\n\n\\\nThis module is designed to try to give you a glimpse of real\npsychological research - and introduce some of the real challenges\n\n. . .\n\n## PS51010C - Extended Essay\n\n-   [3000 words MAX]{.takeaway}\n\n-   [4 x Target Articles (Empirical from the last 3 years)]{.takeaway}\n\n-   [You choose your own topic!]{.takeaway}\n\n-   Make sure to really delve into the **Methods** employed! Really\n    scrutinise the tasks!\n\n## More opportunities next year\n\nOnce you've started your Research Journey\\\nSummer Bursary Competition - a number of weeks of paid research\nexperience\n\n## Final Year Dissertation\n\n\\\n45 Credit Module - Independent Research Project\\\n1:1 with a member of staff\n\n\\\nWhatever topic you can agree on (excluding children/clinical/forensic\nsamples)\n\n## For the aspiring researcher\n\n\\\nIn December of your final year you can apply for a 1+3 funded MSc & PhD\nposition\n\n## Research opportunities available all the time. . .\n\nYou are able to ask to join a lab or work with a member of staff at any\ntime\n\n\\\nSome labs have regular meetings and are open to volunteers, some are\nmore informal or even work on a 1:1 basis\n\n\\\nIf you like the research somebody is doing, go and knock on their door!\n\n# Tips and Tricks\n\n------------------------------------------------------------------------\n\n::: callout-tip\n## Tip Number 1\n\nStart poking around in Academic Journals.\n\nMy favourite way to do this is the app Browzine\n\non your computer AND your phone\n\n[Browzine via the\nLibrary](https://browzine.com/libraries/1374/subjects/67/bookcases/169?sort=title)\n:::\n\n------------------------------------------------------------------------\n\n::: callout-tip\n## Tip Number 2\n\nGet to grips with the Library\n\n<https://libguides.gold.ac.uk/psychology>\n:::\n\n------------------------------------------------------------------------\n\n::: callout-tip\n## Tip Number 3\n\nMake Google Scholar your own\n\n![](images/image00034.png)\n:::\n\n------------------------------------------------------------------------\n\n::: callout-tip\n## Tip Number 4\n\nStrategic Searching & Literature Management\n\n[ResearchRabbit.ai](https://researchrabbitapp.com/home) and\n[Zotero](https://www.zotero.org/)\n\nAlways keep your eyes open for\n\n[Annual Reviews of\nPsychology](https://www.annualreviews.org/journal/psych)\n\nSystematic Reviews and Meta-Analyses (Google Advanced Search!)\n:::\n\n------------------------------------------------------------------------\n\n# Let's get going!\n\nThe link to our study for today is available on the VLE. It's called the\n'Lie of the Land' study\n\n------------------------------------------------------------------------\n\n2.5 Credits available today/this week\n\n## The study link\n\n<https://goldpsych.eu.qualtrics.com/jfe/form/SV_ebMllxwNTfXHXRX>\n\n# BREAK\n\n# LittleMonkeyLab\n\n|                                                                                                                                                                                                                                                                                                                                                                                                                                         |\n|:-----------------------------------------------------------------------|\n| \\## Some easy research!                                                                                                                                                                                                                                                                                                                                                                                                                 |\n| `{=html} <iframe width=\"1280\" height=\"720\" src=\"https://learningonscreen.ac.uk/ondemand/embed/prog/11ED256E?bcast=127465838\" title=\"Horizon: The Honesty Experiment\" frameborder=\"0\" allow=\"accelerometer; autoplay; clipboard-write; encrypted-media; gyroscope; picture-in-picture\" allowfullscreen></iframe>` \\## [BBC Horizon: The Honesty Experiment](https://learningonscreen.ac.uk/ondemand/embed/prog/11ED256E?bcast=127465838) |\n| ![](images/image00028.png)                                                                                                                                                                                                                                                                                                                                                                                                              |\n\n![](images/image00005.png){width=\"900\"}\n\n## So why do people lie? @levine2010d\n\n![](images/image00031.png)\n\n## It ain't that bad really!\n\nDeception frequency is significantly correlated to neocortical volume\nacross species @byrne2004a.\n\n. . .\n\nEvolution selects for more and more effective strategies of achieving\nsocial success (including deception, manipulation, alliance formation,\nexploitation of the expertise of others, etc.)\n\n. . .\n\nAnd for the ability to learn and use such strategies.\n\n. . .\n\nSocial success translates into reproductive success!\n\n## Monkey Business see @shultz2022\n\n. . .\n\n\\\nObservations of non-human behaviour of the type led scientists to\nsuggest a positive relationship between brain size and social group\nsize.\n\n. . .\n\n\\\nA bigger brain seems to be found in more complex social environments.\nBut bigger brains are costly.\n\n. . .\n\n\\\nThere has to be a benefit to carrying around this big brain.\n\n## The dynamic social environment see @whiten2018\n\n. . .\\\nThe social world is very complex and the characters in this social world\nare difficult to predict.\n\n. . .\\\nWe usually operate within a status hierarchy which predetermines our\nopportunities. Think of our cheeky little monkey. What did he want?\n\n::: {.incremental .smaller}\n-   Access to food\n-   Access to shelter\n-   Access to mates\n-   Safety and Security of self and offspring\n:::\n\n[Navigating the hierarchy successfully requires cooperation and\ncompetition.]{.takeaway}\n\n## The Machiavellian Intelligence Hypothesis (@byrne2018)\n\nThe Machiavellian Intelligence Hypothesis posits that social demands\nhave driven the evolution of the cognitive facilities humans employ to\nnavigate their social domain.\n\n'Machiavellian' strategies, such as deception, interpersonal\nmanipulation, cooperation, and alliance formation allow individuals to\nachieve higher social and reproductive success.\n\n. . .\\\n\n[Maybe it would help to be a bit more \"Machiavellian\"?]{.takeaway}\n\n## But how can we possibly measure 'Lie Frequency'?\n\n::: columns\n::: column\nSelf- or other-report\n\nDiary study (or similar)\n\nSome kind of app?\n\nMotion capture suits and TV cameras?\n\nExperimental, lab-based research\n:::\n\n::: column\n![](images/image00004.png)\n:::\n:::\n\n## Machiavellianism\n\n. . .\n\nSensitive to social context, and will switch quickly between cooperation\nand competition depending on utility\n\n. . .\n\n\\\nEndorse emotional manipulation and use emotional skills to ingratiate\n\n. . .\n\n\\\nComprises a cynical view of human nature and interpersonal manipulation\ntactics (perception of the world and behaviour)\n\n## Narcissism\n\n. . .\n\nVain, 'grandiose sense of self', with high levels of entitlement\n\n. . .\n\n\\\nThe Narcissist is unique and special\n\n. . .\n\n\\\nNarcissists, as a result of being surrounded by 'mere mortals' may show\nreduced empathy for others and disregard their goals or status\n\n. . .\n\n\\\nNarcissists maintain their grandiose sense of self by seeking out\npraise, adoration, adulation and avoiding realistic feedback\n\nGrandiose/Vulnerable distinction is starting to get hold.\n\n## Psychopathy\n\n. . .\n\nManifest disregard for other people - Low empathy, disruptive behaviours\nverging on bullying or sadism, deception thought to be a central\nfeature.\n\n. . .\n\n\\\nSuperficial charm and glibness. Erratic lifestyle factors and high\nimpulsivity. Extreme reward appetite and low fear of loss or punishment.\nOften related to criminal activity.\n\n. . .\n\n\\\nBoldness, Meanness, Disinhibition is the 3 Factor structure suggested by\nthe Triarchic Model (Patrick 2010, onwards)\n\n## Bonus prize - Sadism\n\n. . .\n\nAs part of the Dark Tetrad, sadism is investigated in its subclinical\nmanifestation---***everyday sadism***.\n\n. . .\n\n\\\nWhen people enjoy watching violent movies or even playing violent games\nas a social escape to manifest their sadistic traits it is referred to\nas ***vicarious sadism***.\n\n. . .\n\n\\\nThere is sometimes an alternative aspect called ***direct sadism***, but\nit is actually far too rare to be useful in most studies.\n\n. . .\n\n\\\nIn turn, higher scores in everyday sadism are associated with injuring\nothers verbally, physically, and/or psychologically, inspired by a\nhedonic value of being cruel.\n\n## For a comprehensive overview\n\n@turi2022a\n\n@bonfa-araujo2022\n\n@levine2022d\n\n@denault2022d\n\n------------------------------------------------------------------------\n\n## The Target Paper @gunderson2022\n\n<https://hyp.is/L4vR9m9QEe2hne9nNT_AIg/link.springer.com/article/10.1007/s42761-022-00126-5>\n\n------------------------------------------------------------------------\n\n## Hypothes.is\n\nhint: Sign up for a Hypothesis account (FREE)\n\nLog in.\n\nThen access the paper here:\n<https://hyp.is/hvUM3m-KEe26bBOBEKqwUQ/link.springer.com/article/10.1007/s42761-022-00126-5>\n\n## References\n","srcMarkdownNoYaml":"\n\n# Overview\n\n. . .\n\n::: {.callout-important appearance=\"minimal\"}\nAs Module Coordinator of Y2 Research Methods - give some forward-looking\nguidance!\n:::\n\n. . .\n\n::: {.callout-caution appearance=\"minimal\"}\nDo the 'Lie of the Land' survey - tap your deception expertise!\n:::\n\n. . .\n\n> BREAK - 10-15 mins\n\n. . .\n\n::: {.callout-important appearance=\"minimal\"}\nA brief overview of my research\n:::\n\n. . .\n\n::: {.callout-tip appearance=\"minimal\"}\nToday's Target Paper\n:::\n\n. . .\n\n::: {.callout-caution appearance=\"minimal\"}\nQuestions *(of which I hear you usually have many!)*\n:::\n\n# *From one Researcher to another... I mean YOU!*\n\n## A brief introduction\n\n::: columns\n::: column\nDr. Gordon Wright\n\nLecturer in Psychology\n\nModule Coordinator - Y2 Research Methods\n\ng.wright\\@gold.ac.uk\n:::\n:::\n\n## But who are you?\n\n. . .\n\n\\\nWhat do I need to know?\n\n. . .\n\n\\\nWhy did you choose to study at Goldsmiths?\n\n. . .\n\n\\\nWhy Psychology?\n\n## Why does that matter this year?\n\n. . .\n\n\\\nThis module is designed to try to give you a glimpse of real\npsychological research - and introduce some of the real challenges\n\n. . .\n\n## PS51010C - Extended Essay\n\n-   [3000 words MAX]{.takeaway}\n\n-   [4 x Target Articles (Empirical from the last 3 years)]{.takeaway}\n\n-   [You choose your own topic!]{.takeaway}\n\n-   Make sure to really delve into the **Methods** employed! Really\n    scrutinise the tasks!\n\n## More opportunities next year\n\nOnce you've started your Research Journey\\\nSummer Bursary Competition - a number of weeks of paid research\nexperience\n\n## Final Year Dissertation\n\n\\\n45 Credit Module - Independent Research Project\\\n1:1 with a member of staff\n\n\\\nWhatever topic you can agree on (excluding children/clinical/forensic\nsamples)\n\n## For the aspiring researcher\n\n\\\nIn December of your final year you can apply for a 1+3 funded MSc & PhD\nposition\n\n## Research opportunities available all the time. . .\n\nYou are able to ask to join a lab or work with a member of staff at any\ntime\n\n\\\nSome labs have regular meetings and are open to volunteers, some are\nmore informal or even work on a 1:1 basis\n\n\\\nIf you like the research somebody is doing, go and knock on their door!\n\n# Tips and Tricks\n\n------------------------------------------------------------------------\n\n::: callout-tip\n## Tip Number 1\n\nStart poking around in Academic Journals.\n\nMy favourite way to do this is the app Browzine\n\non your computer AND your phone\n\n[Browzine via the\nLibrary](https://browzine.com/libraries/1374/subjects/67/bookcases/169?sort=title)\n:::\n\n------------------------------------------------------------------------\n\n::: callout-tip\n## Tip Number 2\n\nGet to grips with the Library\n\n<https://libguides.gold.ac.uk/psychology>\n:::\n\n------------------------------------------------------------------------\n\n::: callout-tip\n## Tip Number 3\n\nMake Google Scholar your own\n\n![](images/image00034.png)\n:::\n\n------------------------------------------------------------------------\n\n::: callout-tip\n## Tip Number 4\n\nStrategic Searching & Literature Management\n\n[ResearchRabbit.ai](https://researchrabbitapp.com/home) and\n[Zotero](https://www.zotero.org/)\n\nAlways keep your eyes open for\n\n[Annual Reviews of\nPsychology](https://www.annualreviews.org/journal/psych)\n\nSystematic Reviews and Meta-Analyses (Google Advanced Search!)\n:::\n\n------------------------------------------------------------------------\n\n# Let's get going!\n\nThe link to our study for today is available on the VLE. It's called the\n'Lie of the Land' study\n\n------------------------------------------------------------------------\n\n2.5 Credits available today/this week\n\n## The study link\n\n<https://goldpsych.eu.qualtrics.com/jfe/form/SV_ebMllxwNTfXHXRX>\n\n# BREAK\n\n# LittleMonkeyLab\n\n|                                                                                                                                                                                                                                                                                                                                                                                                                                         |\n|:-----------------------------------------------------------------------|\n| \\## Some easy research!                                                                                                                                                                                                                                                                                                                                                                                                                 |\n| `{=html} <iframe width=\"1280\" height=\"720\" src=\"https://learningonscreen.ac.uk/ondemand/embed/prog/11ED256E?bcast=127465838\" title=\"Horizon: The Honesty Experiment\" frameborder=\"0\" allow=\"accelerometer; autoplay; clipboard-write; encrypted-media; gyroscope; picture-in-picture\" allowfullscreen></iframe>` \\## [BBC Horizon: The Honesty Experiment](https://learningonscreen.ac.uk/ondemand/embed/prog/11ED256E?bcast=127465838) |\n| ![](images/image00028.png)                                                                                                                                                                                                                                                                                                                                                                                                              |\n\n![](images/image00005.png){width=\"900\"}\n\n## So why do people lie? @levine2010d\n\n![](images/image00031.png)\n\n## It ain't that bad really!\n\nDeception frequency is significantly correlated to neocortical volume\nacross species @byrne2004a.\n\n. . .\n\nEvolution selects for more and more effective strategies of achieving\nsocial success (including deception, manipulation, alliance formation,\nexploitation of the expertise of others, etc.)\n\n. . .\n\nAnd for the ability to learn and use such strategies.\n\n. . .\n\nSocial success translates into reproductive success!\n\n## Monkey Business see @shultz2022\n\n. . .\n\n\\\nObservations of non-human behaviour of the type led scientists to\nsuggest a positive relationship between brain size and social group\nsize.\n\n. . .\n\n\\\nA bigger brain seems to be found in more complex social environments.\nBut bigger brains are costly.\n\n. . .\n\n\\\nThere has to be a benefit to carrying around this big brain.\n\n## The dynamic social environment see @whiten2018\n\n. . .\\\nThe social world is very complex and the characters in this social world\nare difficult to predict.\n\n. . .\\\nWe usually operate within a status hierarchy which predetermines our\nopportunities. Think of our cheeky little monkey. What did he want?\n\n::: {.incremental .smaller}\n-   Access to food\n-   Access to shelter\n-   Access to mates\n-   Safety and Security of self and offspring\n:::\n\n[Navigating the hierarchy successfully requires cooperation and\ncompetition.]{.takeaway}\n\n## The Machiavellian Intelligence Hypothesis (@byrne2018)\n\nThe Machiavellian Intelligence Hypothesis posits that social demands\nhave driven the evolution of the cognitive facilities humans employ to\nnavigate their social domain.\n\n'Machiavellian' strategies, such as deception, interpersonal\nmanipulation, cooperation, and alliance formation allow individuals to\nachieve higher social and reproductive success.\n\n. . .\\\n\n[Maybe it would help to be a bit more \"Machiavellian\"?]{.takeaway}\n\n## But how can we possibly measure 'Lie Frequency'?\n\n::: columns\n::: column\nSelf- or other-report\n\nDiary study (or similar)\n\nSome kind of app?\n\nMotion capture suits and TV cameras?\n\nExperimental, lab-based research\n:::\n\n::: column\n![](images/image00004.png)\n:::\n:::\n\n## Machiavellianism\n\n. . .\n\nSensitive to social context, and will switch quickly between cooperation\nand competition depending on utility\n\n. . .\n\n\\\nEndorse emotional manipulation and use emotional skills to ingratiate\n\n. . .\n\n\\\nComprises a cynical view of human nature and interpersonal manipulation\ntactics (perception of the world and behaviour)\n\n## Narcissism\n\n. . .\n\nVain, 'grandiose sense of self', with high levels of entitlement\n\n. . .\n\n\\\nThe Narcissist is unique and special\n\n. . .\n\n\\\nNarcissists, as a result of being surrounded by 'mere mortals' may show\nreduced empathy for others and disregard their goals or status\n\n. . .\n\n\\\nNarcissists maintain their grandiose sense of self by seeking out\npraise, adoration, adulation and avoiding realistic feedback\n\nGrandiose/Vulnerable distinction is starting to get hold.\n\n## Psychopathy\n\n. . .\n\nManifest disregard for other people - Low empathy, disruptive behaviours\nverging on bullying or sadism, deception thought to be a central\nfeature.\n\n. . .\n\n\\\nSuperficial charm and glibness. Erratic lifestyle factors and high\nimpulsivity. Extreme reward appetite and low fear of loss or punishment.\nOften related to criminal activity.\n\n. . .\n\n\\\nBoldness, Meanness, Disinhibition is the 3 Factor structure suggested by\nthe Triarchic Model (Patrick 2010, onwards)\n\n## Bonus prize - Sadism\n\n. . .\n\nAs part of the Dark Tetrad, sadism is investigated in its subclinical\nmanifestation---***everyday sadism***.\n\n. . .\n\n\\\nWhen people enjoy watching violent movies or even playing violent games\nas a social escape to manifest their sadistic traits it is referred to\nas ***vicarious sadism***.\n\n. . .\n\n\\\nThere is sometimes an alternative aspect called ***direct sadism***, but\nit is actually far too rare to be useful in most studies.\n\n. . .\n\n\\\nIn turn, higher scores in everyday sadism are associated with injuring\nothers verbally, physically, and/or psychologically, inspired by a\nhedonic value of being cruel.\n\n## For a comprehensive overview\n\n@turi2022a\n\n@bonfa-araujo2022\n\n@levine2022d\n\n@denault2022d\n\n------------------------------------------------------------------------\n\n## The Target Paper @gunderson2022\n\n<https://hyp.is/L4vR9m9QEe2hne9nNT_AIg/link.springer.com/article/10.1007/s42761-022-00126-5>\n\n------------------------------------------------------------------------\n\n## Hypothes.is\n\nhint: Sign up for a Hypothesis account (FREE)\n\nLog in.\n\nThen access the paper here:\n<https://hyp.is/hvUM3m-KEe26bBOBEKqwUQ/link.springer.com/article/10.1007/s42761-022-00126-5>\n\n## References\n"},"formats":{"pdf":{"identifier":{"display-name":"PDF","target-format":"pdf","base-format":"pdf"},"execute":{"fig-width":5.5,"fig-height":3.5,"fig-format":"pdf","fig-dpi":300,"df-print":"default","error":false,"eval":true,"cache":null,"freeze":"auto","echo":false,"output":true,"warning":true,"include":true,"keep-md":false,"keep-ipynb":false,"ipynb":null,"enabled":null,"daemon":null,"daemon-restart":false,"debug":false,"ipynb-filters":[],"ipynb-shell-interactivity":null,"plotly-connected":true,"engine":"markdown"},"render":{"keep-tex":false,"keep-typ":false,"keep-source":false,"keep-hidden":false,"prefer-html":false,"output-divs":true,"output-ext":"pdf","fig-align":"default","fig-pos":null,"fig-env":null,"code-fold":"none","code-overflow":"scroll","code-link":false,"code-line-numbers":false,"code-tools":false,"tbl-colwidths":true,"merge-includes":true,"inline-includes":false,"preserve-yaml":false,"latex-auto-mk":true,"latex-auto-install":true,"latex-clean":true,"latex-min-runs":1,"latex-max-runs":10,"latex-makeindex":"makeindex","latex-makeindex-opts":[],"latex-tlmgr-opts":[],"latex-input-paths":[],"latex-output-dir":null,"link-external-icon":false,"link-external-newwindow":false,"self-contained-math":false,"format-resources":[]},"pandoc":{"pdf-engine":"xelatex","standalone":true,"variables":{"graphics":true,"tables":true},"default-image-extension":"pdf","to":"pdf","citeproc":true,"toc":false,"include-in-header":{"text":"\\usepackage{fancyhdr}\n\\pagestyle{fancy}\n\\fancyhead[L]{Week 02}\n\\fancyhead[R]{Dr. Gordon Wright}\n\\fancyfoot[R]{PS52007D - Research Methods}\n\\fancyfoot[C]{\\thepage}\n\\fancyfoot[L]{CC BY-SA 4.0}\n\\renewcommand{\\headrulewidth}{0.4pt}\n\\renewcommand{\\footrulewidth}{0.4pt}\n"},"include-before-body":{"text":"\\raggedright\n"},"filters":["reveal-header"],"embed-resources":true,"output-file":"lecture.pdf"},"language":{"toc-title-document":"Table of contents","toc-title-website":"On this page","related-formats-title":"Other Formats","related-notebooks-title":"Notebooks","source-notebooks-prefix":"Source","other-links-title":"Other Links","code-links-title":"Code Links","launch-dev-container-title":"Launch Dev Container","launch-binder-title":"Launch Binder","article-notebook-label":"Article Notebook","notebook-preview-download":"Download Notebook","notebook-preview-download-src":"Download Source","notebook-preview-back":"Back to Article","manuscript-meca-bundle":"MECA Bundle","section-title-abstract":"Abstract","section-title-appendices":"Appendices","section-title-footnotes":"Footnotes","section-title-references":"References","section-title-reuse":"Reuse","section-title-copyright":"Copyright","section-title-citation":"Citation","appendix-attribution-cite-as":"For attribution, please cite this work as:","appendix-attribution-bibtex":"BibTeX citation:","title-block-author-single":"Author","title-block-author-plural":"Authors","title-block-affiliation-single":"Affiliation","title-block-affiliation-plural":"Affiliations","title-block-published":"Published","title-block-modified":"Modified","title-block-keywords":"Keywords","callout-tip-title":"Tip","callout-note-title":"Note","callout-warning-title":"Warning","callout-important-title":"Important","callout-caution-title":"Caution","code-summary":"Code","code-tools-menu-caption":"Code","code-tools-show-all-code":"Show All Code","code-tools-hide-all-code":"Hide All Code","code-tools-view-source":"View Source","code-tools-source-code":"Source Code","code-line":"Line","code-lines":"Lines","copy-button-tooltip":"Copy to Clipboard","copy-button-tooltip-success":"Copied!","repo-action-links-edit":"Edit this page","repo-action-links-source":"View source","repo-action-links-issue":"Report an issue","back-to-top":"Back to top","search-no-results-text":"No results","search-matching-documents-text":"matching documents","search-copy-link-title":"Copy link to search","search-hide-matches-text":"Hide additional matches","search-more-match-text":"more match in this document","search-more-matches-text":"more matches in this document","search-clear-button-title":"Clear","search-text-placeholder":"","search-detached-cancel-button-title":"Cancel","search-submit-button-title":"Submit","search-label":"Search","toggle-section":"Toggle section","toggle-sidebar":"Toggle sidebar navigation","toggle-dark-mode":"Toggle dark mode","toggle-reader-mode":"Toggle reader mode","toggle-navigation":"Toggle navigation","crossref-fig-title":"Figure","crossref-tbl-title":"Table","crossref-lst-title":"Listing","crossref-thm-title":"Theorem","crossref-lem-title":"Lemma","crossref-cor-title":"Corollary","crossref-prp-title":"Proposition","crossref-cnj-title":"Conjecture","crossref-def-title":"Definition","crossref-exm-title":"Example","crossref-exr-title":"Exercise","crossref-ch-prefix":"Chapter","crossref-apx-prefix":"Appendix","crossref-sec-prefix":"Section","crossref-eq-prefix":"Equation","crossref-lof-title":"List of Figures","crossref-lot-title":"List of Tables","crossref-lol-title":"List of Listings","environment-proof-title":"Proof","environment-remark-title":"Remark","environment-solution-title":"Solution","listing-page-order-by":"Order By","listing-page-order-by-default":"Default","listing-page-order-by-date-asc":"Oldest","listing-page-order-by-date-desc":"Newest","listing-page-order-by-number-desc":"High to Low","listing-page-order-by-number-asc":"Low to High","listing-page-field-date":"Date","listing-page-field-title":"Title","listing-page-field-description":"Description","listing-page-field-author":"Author","listing-page-field-filename":"File Name","listing-page-field-filemodified":"Modified","listing-page-field-subtitle":"Subtitle","listing-page-field-readingtime":"Reading Time","listing-page-field-wordcount":"Word Count","listing-page-field-categories":"Categories","listing-page-minutes-compact":"{0} min","listing-page-category-all":"All","listing-page-no-matches":"No matching items","listing-page-words":"{0} words"},"metadata":{"block-headings":true,"modulecode":"PS52007D","bibliography":["../../references.bib","../../textbook.bib"],"csl":"../../apa7.csl","date-format":"long","_quarto-vars":{"author":"Gordon Wright","email":"g.wright@gold.ac.uk","instructor":{"name":"Dr. Gordon Wright","name_no_title":"Gordon Wright","email":"g.wright@gold.ac.uk","url":"www.littlemonkeylab.com","twitter":"drdeception","github":"LittleMonkeyLab","office":"Whitehead 200/1","contact_policy":"E-mail is the best ways to get in contact with me. I will try to respond to all course-related e-mails within 24 hours. Any questions relating to the course, coursework or anything not personal/confidential in nature should be submitted to the Course Forum. This benefits all students. So, if you email me about the course, don't be surprised if you get a brief 'Please post this to the Forum' message!   Office hours are advertised on the module VLE page."},"course":{"number":"PS52007D","semester":"Academic Year 2023-4","days":"Monday Lecture | Tuesday Labs","time":"10am","location":"PSH LG02","dates":"October to March, 2023-4","github":"https://www.github.com/littlemonkeylab/PS52007D_2023-4","url":"https://littlemonkeylab.com/PS52007D_2023-4","copyright_year":"2023"},"university":{"name":"Goldsmiths, University of London","url":"https://www.gold.ac.uk"},"school":{"name":"Department of Psychology","url":"https://gold.ac.uk/psychology"}},"comments":{"hypothesis":{"theme":"clean","openSidebar":false}},"mainfont":"Atkinson Hyperlegible","sansfont":"Atkinson Hyperlegible","monofont":"Fira Code","editor":"visual","title":"Practical Issues 2023: Deviously Seeking Duping Delight in the Dark","subtitle":"LittleMonkeyLab","image":"lecture.png","author":[{"name":"Dr. Gordon Wright","orcid":"0000-0001-9424-5743","email":"g.wright@gold.ac.uk"}],"date":"10/31/2023","license":"CC BY-NC-SA","citations-hover":true,"categories":["Lecture","Week 21"],"params":{"class":"lec21"}},"extensions":{"book":{"selfContainedOutput":true}}},"pptx":{"identifier":{"display-name":"Powerpoint","target-format":"pptx","base-format":"pptx"},"execute":{"fig-width":11,"fig-height":5.5,"fig-format":"png","fig-dpi":96,"df-print":"default","error":false,"eval":true,"cache":null,"freeze":"auto","echo":false,"output":true,"warning":false,"include":true,"keep-md":false,"keep-ipynb":false,"ipynb":null,"enabled":null,"daemon":null,"daemon-restart":false,"debug":false,"ipynb-filters":[],"ipynb-shell-interactivity":null,"plotly-connected":true,"engine":"markdown"},"render":{"keep-tex":false,"keep-typ":false,"keep-source":false,"keep-hidden":false,"prefer-html":false,"output-divs":false,"output-ext":"pptx","fig-align":"default","fig-pos":null,"fig-env":null,"code-fold":"none","code-overflow":"scroll","code-link":false,"code-line-numbers":false,"code-tools":false,"tbl-colwidths":true,"merge-includes":true,"inline-includes":false,"preserve-yaml":false,"latex-auto-mk":true,"latex-auto-install":true,"latex-clean":true,"latex-min-runs":1,"latex-max-runs":10,"latex-makeindex":"makeindex","latex-makeindex-opts":[],"latex-tlmgr-opts":[],"latex-input-paths":[],"latex-output-dir":null,"link-external-icon":false,"link-external-newwindow":false,"self-contained-math":false,"format-resources":[],"page-width":10},"pandoc":{"default-image-extension":"png","to":"pptx","citeproc":true,"reference-doc":"../_resources/templates/pptx/RMLecturepptxTemplate.pptx","filters":["reveal-header"],"embed-resources":true,"output-file":"lecture.pptx"},"language":{"toc-title-document":"Table of contents","toc-title-website":"On this page","related-formats-title":"Other Formats","related-notebooks-title":"Notebooks","source-notebooks-prefix":"Source","other-links-title":"Other Links","code-links-title":"Code Links","launch-dev-container-title":"Launch Dev Container","launch-binder-title":"Launch Binder","article-notebook-label":"Article Notebook","notebook-preview-download":"Download Notebook","notebook-preview-download-src":"Download Source","notebook-preview-back":"Back to Article","manuscript-meca-bundle":"MECA Bundle","section-title-abstract":"Abstract","section-title-appendices":"Appendices","section-title-footnotes":"Footnotes","section-title-references":"References","section-title-reuse":"Reuse","section-title-copyright":"Copyright","section-title-citation":"Citation","appendix-attribution-cite-as":"For attribution, please cite this work as:","appendix-attribution-bibtex":"BibTeX citation:","title-block-author-single":"Author","title-block-author-plural":"Authors","title-block-affiliation-single":"Affiliation","title-block-affiliation-plural":"Affiliations","title-block-published":"Published","title-block-modified":"Modified","title-block-keywords":"Keywords","callout-tip-title":"Tip","callout-note-title":"Note","callout-warning-title":"Warning","callout-important-title":"Important","callout-caution-title":"Caution","code-summary":"Code","code-tools-menu-caption":"Code","code-tools-show-all-code":"Show All Code","code-tools-hide-all-code":"Hide All Code","code-tools-view-source":"View Source","code-tools-source-code":"Source Code","code-line":"Line","code-lines":"Lines","copy-button-tooltip":"Copy to Clipboard","copy-button-tooltip-success":"Copied!","repo-action-links-edit":"Edit this page","repo-action-links-source":"View source","repo-action-links-issue":"Report an issue","back-to-top":"Back to top","search-no-results-text":"No results","search-matching-documents-text":"matching documents","search-copy-link-title":"Copy link to search","search-hide-matches-text":"Hide additional matches","search-more-match-text":"more match in this document","search-more-matches-text":"more matches in this document","search-clear-button-title":"Clear","search-text-placeholder":"","search-detached-cancel-button-title":"Cancel","search-submit-button-title":"Submit","search-label":"Search","toggle-section":"Toggle section","toggle-sidebar":"Toggle sidebar navigation","toggle-dark-mode":"Toggle dark mode","toggle-reader-mode":"Toggle reader mode","toggle-navigation":"Toggle navigation","crossref-fig-title":"Figure","crossref-tbl-title":"Table","crossref-lst-title":"Listing","crossref-thm-title":"Theorem","crossref-lem-title":"Lemma","crossref-cor-title":"Corollary","crossref-prp-title":"Proposition","crossref-cnj-title":"Conjecture","crossref-def-title":"Definition","crossref-exm-title":"Example","crossref-exr-title":"Exercise","crossref-ch-prefix":"Chapter","crossref-apx-prefix":"Appendix","crossref-sec-prefix":"Section","crossref-eq-prefix":"Equation","crossref-lof-title":"List of Figures","crossref-lot-title":"List of Tables","crossref-lol-title":"List of Listings","environment-proof-title":"Proof","environment-remark-title":"Remark","environment-solution-title":"Solution","listing-page-order-by":"Order By","listing-page-order-by-default":"Default","listing-page-order-by-date-asc":"Oldest","listing-page-order-by-date-desc":"Newest","listing-page-order-by-number-desc":"High to Low","listing-page-order-by-number-asc":"Low to High","listing-page-field-date":"Date","listing-page-field-title":"Title","listing-page-field-description":"Description","listing-page-field-author":"Author","listing-page-field-filename":"File Name","listing-page-field-filemodified":"Modified","listing-page-field-subtitle":"Subtitle","listing-page-field-readingtime":"Reading Time","listing-page-field-wordcount":"Word Count","listing-page-field-categories":"Categories","listing-page-minutes-compact":"{0} min","listing-page-category-all":"All","listing-page-no-matches":"No matching items","listing-page-words":"{0} words"},"metadata":{"modulecode":"PS52007D","bibliography":["../../references.bib","../../textbook.bib"],"csl":"../../apa7.csl","date-format":"long","_quarto-vars":{"author":"Gordon Wright","email":"g.wright@gold.ac.uk","instructor":{"name":"Dr. Gordon Wright","name_no_title":"Gordon Wright","email":"g.wright@gold.ac.uk","url":"www.littlemonkeylab.com","twitter":"drdeception","github":"LittleMonkeyLab","office":"Whitehead 200/1","contact_policy":"E-mail is the best ways to get in contact with me. I will try to respond to all course-related e-mails within 24 hours. Any questions relating to the course, coursework or anything not personal/confidential in nature should be submitted to the Course Forum. This benefits all students. So, if you email me about the course, don't be surprised if you get a brief 'Please post this to the Forum' message!   Office hours are advertised on the module VLE page."},"course":{"number":"PS52007D","semester":"Academic Year 2023-4","days":"Monday Lecture | Tuesday Labs","time":"10am","location":"PSH LG02","dates":"October to March, 2023-4","github":"https://www.github.com/littlemonkeylab/PS52007D_2023-4","url":"https://littlemonkeylab.com/PS52007D_2023-4","copyright_year":"2023"},"university":{"name":"Goldsmiths, University of London","url":"https://www.gold.ac.uk"},"school":{"name":"Department of Psychology","url":"https://gold.ac.uk/psychology"}},"comments":{"hypothesis":{"theme":"clean","openSidebar":false}},"editor":"visual","title":"Practical Issues 2023: Deviously Seeking Duping Delight in the Dark","subtitle":"LittleMonkeyLab","image":"lecture.png","author":[{"name":"Dr. Gordon Wright","orcid":"0000-0001-9424-5743","email":"g.wright@gold.ac.uk"}],"date":"10/31/2023","license":"CC BY-NC-SA","citations-hover":true,"categories":["Lecture","Week 21"],"params":{"class":"lec21"}}},"html":{"identifier":{"display-name":"HTML","target-format":"html","base-format":"html"},"execute":{"fig-width":7,"fig-height":5,"fig-format":"retina","fig-dpi":96,"df-print":"default","error":false,"eval":true,"cache":null,"freeze":"auto","echo":false,"output":true,"warning":true,"include":true,"keep-md":false,"keep-ipynb":false,"ipynb":null,"enabled":null,"daemon":null,"daemon-restart":false,"debug":false,"ipynb-filters":[],"ipynb-shell-interactivity":null,"plotly-connected":true,"engine":"markdown"},"render":{"keep-tex":false,"keep-typ":false,"keep-source":false,"keep-hidden":false,"prefer-html":false,"output-divs":true,"output-ext":"html","fig-align":"default","fig-pos":null,"fig-env":null,"code-fold":true,"code-overflow":"wrap","code-link":false,"code-line-numbers":false,"code-tools":false,"tbl-colwidths":"auto","merge-includes":true,"inline-includes":false,"preserve-yaml":false,"latex-auto-mk":true,"latex-auto-install":true,"latex-clean":true,"latex-min-runs":1,"latex-max-runs":10,"latex-makeindex":"makeindex","latex-makeindex-opts":[],"latex-tlmgr-opts":[],"latex-input-paths":[],"latex-output-dir":null,"link-external-icon":false,"link-external-newwindow":false,"self-contained-math":false,"format-resources":[],"notebook-links":true},"pandoc":{"standalone":true,"wrap":"none","default-image-extension":"png","to":"html","citeproc":true,"toc":true,"embed-resources":true,"css":["../../include/webex.css","../../styles.css"],"include-after-body":["../../include/webex.js"],"filters":["fontawesome","reveal-header"],"output-file":"lecture.html"},"language":{"toc-title-document":"Table of contents","toc-title-website":"On this page","related-formats-title":"Other Formats","related-notebooks-title":"Notebooks","source-notebooks-prefix":"Source","other-links-title":"Other Links","code-links-title":"Code Links","launch-dev-container-title":"Launch Dev Container","launch-binder-title":"Launch Binder","article-notebook-label":"Article Notebook","notebook-preview-download":"Download Notebook","notebook-preview-download-src":"Download Source","notebook-preview-back":"Back to Article","manuscript-meca-bundle":"MECA Bundle","section-title-abstract":"Abstract","section-title-appendices":"Appendices","section-title-footnotes":"Footnotes","section-title-references":"References","section-title-reuse":"Reuse","section-title-copyright":"Copyright","section-title-citation":"Citation","appendix-attribution-cite-as":"For attribution, please cite this work as:","appendix-attribution-bibtex":"BibTeX citation:","title-block-author-single":"Author","title-block-author-plural":"Authors","title-block-affiliation-single":"Affiliation","title-block-affiliation-plural":"Affiliations","title-block-published":"Published","title-block-modified":"Modified","title-block-keywords":"Keywords","callout-tip-title":"Tip","callout-note-title":"Note","callout-warning-title":"Warning","callout-important-title":"Important","callout-caution-title":"Caution","code-summary":"Code","code-tools-menu-caption":"Code","code-tools-show-all-code":"Show All Code","code-tools-hide-all-code":"Hide All Code","code-tools-view-source":"View Source","code-tools-source-code":"Source Code","code-line":"Line","code-lines":"Lines","copy-button-tooltip":"Copy to Clipboard","copy-button-tooltip-success":"Copied!","repo-action-links-edit":"Edit this page","repo-action-links-source":"View source","repo-action-links-issue":"Report an issue","back-to-top":"Back to top","search-no-results-text":"No results","search-matching-documents-text":"matching documents","search-copy-link-title":"Copy link to search","search-hide-matches-text":"Hide additional matches","search-more-match-text":"more match in this document","search-more-matches-text":"more matches in this document","search-clear-button-title":"Clear","search-text-placeholder":"","search-detached-cancel-button-title":"Cancel","search-submit-button-title":"Submit","search-label":"Search","toggle-section":"Toggle section","toggle-sidebar":"Toggle sidebar navigation","toggle-dark-mode":"Toggle dark mode","toggle-reader-mode":"Toggle reader mode","toggle-navigation":"Toggle navigation","crossref-fig-title":"Figure","crossref-tbl-title":"Table","crossref-lst-title":"Listing","crossref-thm-title":"Theorem","crossref-lem-title":"Lemma","crossref-cor-title":"Corollary","crossref-prp-title":"Proposition","crossref-cnj-title":"Conjecture","crossref-def-title":"Definition","crossref-exm-title":"Example","crossref-exr-title":"Exercise","crossref-ch-prefix":"Chapter","crossref-apx-prefix":"Appendix","crossref-sec-prefix":"Section","crossref-eq-prefix":"Equation","crossref-lof-title":"List of Figures","crossref-lot-title":"List of Tables","crossref-lol-title":"List of Listings","environment-proof-title":"Proof","environment-remark-title":"Remark","environment-solution-title":"Solution","listing-page-order-by":"Order By","listing-page-order-by-default":"Default","listing-page-order-by-date-asc":"Oldest","listing-page-order-by-date-desc":"Newest","listing-page-order-by-number-desc":"High to Low","listing-page-order-by-number-asc":"Low to High","listing-page-field-date":"Date","listing-page-field-title":"Title","listing-page-field-description":"Description","listing-page-field-author":"Author","listing-page-field-filename":"File Name","listing-page-field-filemodified":"Modified","listing-page-field-subtitle":"Subtitle","listing-page-field-readingtime":"Reading Time","listing-page-field-wordcount":"Word Count","listing-page-field-categories":"Categories","listing-page-minutes-compact":"{0} min","listing-page-category-all":"All","listing-page-no-matches":"No matching items","listing-page-words":"{0} words"},"metadata":{"lang":"en","fig-responsive":true,"quarto-version":"1.4.533","modulecode":"PS52007D","bibliography":["../../references.bib","../../textbook.bib"],"csl":"../../apa7.csl","date-format":"long","_quarto-vars":{"author":"Gordon Wright","email":"g.wright@gold.ac.uk","instructor":{"name":"Dr. Gordon Wright","name_no_title":"Gordon Wright","email":"g.wright@gold.ac.uk","url":"www.littlemonkeylab.com","twitter":"drdeception","github":"LittleMonkeyLab","office":"Whitehead 200/1","contact_policy":"E-mail is the best ways to get in contact with me. I will try to respond to all course-related e-mails within 24 hours. Any questions relating to the course, coursework or anything not personal/confidential in nature should be submitted to the Course Forum. This benefits all students. So, if you email me about the course, don't be surprised if you get a brief 'Please post this to the Forum' message!   Office hours are advertised on the module VLE page."},"course":{"number":"PS52007D","semester":"Academic Year 2023-4","days":"Monday Lecture | Tuesday Labs","time":"10am","location":"PSH LG02","dates":"October to March, 2023-4","github":"https://www.github.com/littlemonkeylab/PS52007D_2023-4","url":"https://littlemonkeylab.com/PS52007D_2023-4","copyright_year":"2023"},"university":{"name":"Goldsmiths, University of London","url":"https://www.gold.ac.uk"},"school":{"name":"Department of Psychology","url":"https://gold.ac.uk/psychology"}},"comments":{"hypothesis":{"theme":"clean","openSidebar":false}},"theme":"simplex","mainfont":"Atkinson Hyperlegible","monofont":"Fira Code","linkcolor":"#BE3455","grid":{"sidebar-width":"250px","body-width":"900px","margin-width":"300px"},"editor":"visual","title":"Practical Issues 2023: Deviously Seeking Duping Delight in the Dark","subtitle":"LittleMonkeyLab","image":"lecture.png","author":[{"name":"Dr. Gordon Wright","orcid":"0000-0001-9424-5743","email":"g.wright@gold.ac.uk"}],"date":"10/31/2023","license":"CC BY-NC-SA","citations-hover":true,"categories":["Lecture","Week 21"],"params":{"class":"lec21"}},"extensions":{"book":{"multiFile":true}}},"docx":{"identifier":{"display-name":"MS Word","target-format":"docx","base-format":"docx"},"execute":{"fig-width":5,"fig-height":4,"fig-format":"png","fig-dpi":96,"df-print":"default","error":false,"eval":true,"cache":null,"freeze":"auto","echo":false,"output":true,"warning":true,"include":true,"keep-md":false,"keep-ipynb":false,"ipynb":null,"enabled":null,"daemon":null,"daemon-restart":false,"debug":false,"ipynb-filters":[],"ipynb-shell-interactivity":null,"plotly-connected":true,"engine":"markdown"},"render":{"keep-tex":false,"keep-typ":false,"keep-source":false,"keep-hidden":false,"prefer-html":false,"output-divs":true,"output-ext":"docx","fig-align":"default","fig-pos":null,"fig-env":null,"code-fold":"none","code-overflow":"scroll","code-link":false,"code-line-numbers":false,"code-tools":false,"tbl-colwidths":true,"merge-includes":true,"inline-includes":false,"preserve-yaml":false,"latex-auto-mk":true,"latex-auto-install":true,"latex-clean":true,"latex-min-runs":1,"latex-max-runs":10,"latex-makeindex":"makeindex","latex-makeindex-opts":[],"latex-tlmgr-opts":[],"latex-input-paths":[],"latex-output-dir":null,"link-external-icon":false,"link-external-newwindow":false,"self-contained-math":false,"format-resources":[],"page-width":6.5},"pandoc":{"default-image-extension":"png","to":"docx","citeproc":true,"filters":["reveal-header"],"embed-resources":true,"output-file":"lecture.docx"},"language":{"toc-title-document":"Table of contents","toc-title-website":"On this page","related-formats-title":"Other Formats","related-notebooks-title":"Notebooks","source-notebooks-prefix":"Source","other-links-title":"Other Links","code-links-title":"Code Links","launch-dev-container-title":"Launch Dev Container","launch-binder-title":"Launch Binder","article-notebook-label":"Article Notebook","notebook-preview-download":"Download Notebook","notebook-preview-download-src":"Download Source","notebook-preview-back":"Back to Article","manuscript-meca-bundle":"MECA Bundle","section-title-abstract":"Abstract","section-title-appendices":"Appendices","section-title-footnotes":"Footnotes","section-title-references":"References","section-title-reuse":"Reuse","section-title-copyright":"Copyright","section-title-citation":"Citation","appendix-attribution-cite-as":"For attribution, please cite this work as:","appendix-attribution-bibtex":"BibTeX citation:","title-block-author-single":"Author","title-block-author-plural":"Authors","title-block-affiliation-single":"Affiliation","title-block-affiliation-plural":"Affiliations","title-block-published":"Published","title-block-modified":"Modified","title-block-keywords":"Keywords","callout-tip-title":"Tip","callout-note-title":"Note","callout-warning-title":"Warning","callout-important-title":"Important","callout-caution-title":"Caution","code-summary":"Code","code-tools-menu-caption":"Code","code-tools-show-all-code":"Show All Code","code-tools-hide-all-code":"Hide All Code","code-tools-view-source":"View Source","code-tools-source-code":"Source Code","code-line":"Line","code-lines":"Lines","copy-button-tooltip":"Copy to Clipboard","copy-button-tooltip-success":"Copied!","repo-action-links-edit":"Edit this page","repo-action-links-source":"View source","repo-action-links-issue":"Report an issue","back-to-top":"Back to top","search-no-results-text":"No results","search-matching-documents-text":"matching documents","search-copy-link-title":"Copy link to search","search-hide-matches-text":"Hide additional matches","search-more-match-text":"more match in this document","search-more-matches-text":"more matches in this document","search-clear-button-title":"Clear","search-text-placeholder":"","search-detached-cancel-button-title":"Cancel","search-submit-button-title":"Submit","search-label":"Search","toggle-section":"Toggle section","toggle-sidebar":"Toggle sidebar navigation","toggle-dark-mode":"Toggle dark mode","toggle-reader-mode":"Toggle reader mode","toggle-navigation":"Toggle navigation","crossref-fig-title":"Figure","crossref-tbl-title":"Table","crossref-lst-title":"Listing","crossref-thm-title":"Theorem","crossref-lem-title":"Lemma","crossref-cor-title":"Corollary","crossref-prp-title":"Proposition","crossref-cnj-title":"Conjecture","crossref-def-title":"Definition","crossref-exm-title":"Example","crossref-exr-title":"Exercise","crossref-ch-prefix":"Chapter","crossref-apx-prefix":"Appendix","crossref-sec-prefix":"Section","crossref-eq-prefix":"Equation","crossref-lof-title":"List of Figures","crossref-lot-title":"List of Tables","crossref-lol-title":"List of Listings","environment-proof-title":"Proof","environment-remark-title":"Remark","environment-solution-title":"Solution","listing-page-order-by":"Order By","listing-page-order-by-default":"Default","listing-page-order-by-date-asc":"Oldest","listing-page-order-by-date-desc":"Newest","listing-page-order-by-number-desc":"High to Low","listing-page-order-by-number-asc":"Low to High","listing-page-field-date":"Date","listing-page-field-title":"Title","listing-page-field-description":"Description","listing-page-field-author":"Author","listing-page-field-filename":"File Name","listing-page-field-filemodified":"Modified","listing-page-field-subtitle":"Subtitle","listing-page-field-readingtime":"Reading Time","listing-page-field-wordcount":"Word Count","listing-page-field-categories":"Categories","listing-page-minutes-compact":"{0} min","listing-page-category-all":"All","listing-page-no-matches":"No matching items","listing-page-words":"{0} words"},"metadata":{"modulecode":"PS52007D","bibliography":["../../references.bib","../../textbook.bib"],"csl":"../../apa7.csl","date-format":"long","_quarto-vars":{"author":"Gordon Wright","email":"g.wright@gold.ac.uk","instructor":{"name":"Dr. Gordon Wright","name_no_title":"Gordon Wright","email":"g.wright@gold.ac.uk","url":"www.littlemonkeylab.com","twitter":"drdeception","github":"LittleMonkeyLab","office":"Whitehead 200/1","contact_policy":"E-mail is the best ways to get in contact with me. I will try to respond to all course-related e-mails within 24 hours. Any questions relating to the course, coursework or anything not personal/confidential in nature should be submitted to the Course Forum. This benefits all students. So, if you email me about the course, don't be surprised if you get a brief 'Please post this to the Forum' message!   Office hours are advertised on the module VLE page."},"course":{"number":"PS52007D","semester":"Academic Year 2023-4","days":"Monday Lecture | Tuesday Labs","time":"10am","location":"PSH LG02","dates":"October to March, 2023-4","github":"https://www.github.com/littlemonkeylab/PS52007D_2023-4","url":"https://littlemonkeylab.com/PS52007D_2023-4","copyright_year":"2023"},"university":{"name":"Goldsmiths, University of London","url":"https://www.gold.ac.uk"},"school":{"name":"Department of Psychology","url":"https://gold.ac.uk/psychology"}},"comments":{"hypothesis":{"theme":"clean","openSidebar":false}},"editor":"visual","title":"Practical Issues 2023: Deviously Seeking Duping Delight in the Dark","subtitle":"LittleMonkeyLab","image":"lecture.png","author":[{"name":"Dr. Gordon Wright","orcid":"0000-0001-9424-5743","email":"g.wright@gold.ac.uk"}],"date":"10/31/2023","license":"CC BY-NC-SA","citations-hover":true,"categories":["Lecture","Week 21"],"params":{"class":"lec21"}},"extensions":{"book":{"selfContainedOutput":true}}},"revealjs":{"identifier":{"display-name":"RevealJS","target-format":"revealjs","base-format":"revealjs"},"execute":{"fig-width":10,"fig-height":5,"fig-format":"retina","fig-dpi":96,"df-print":"default","error":false,"eval":true,"cache":null,"freeze":"auto","echo":false,"output":true,"warning":false,"include":true,"keep-md":false,"keep-ipynb":false,"ipynb":null,"enabled":null,"daemon":null,"daemon-restart":false,"debug":false,"ipynb-filters":[],"ipynb-shell-interactivity":null,"plotly-connected":true,"engine":"markdown"},"render":{"keep-tex":false,"keep-typ":false,"keep-source":false,"keep-hidden":false,"prefer-html":false,"output-divs":true,"output-ext":"slides.html","fig-align":"default","fig-pos":null,"fig-env":null,"code-fold":"none","code-overflow":"scroll","code-link":false,"code-line-numbers":true,"code-tools":false,"tbl-colwidths":"auto","merge-includes":true,"inline-includes":false,"preserve-yaml":false,"latex-auto-mk":true,"latex-auto-install":true,"latex-clean":true,"latex-min-runs":1,"latex-max-runs":10,"latex-makeindex":"makeindex","latex-makeindex-opts":[],"latex-tlmgr-opts":[],"latex-input-paths":[],"latex-output-dir":null,"link-external-icon":false,"link-external-newwindow":false,"self-contained-math":false,"format-resources":[]},"pandoc":{"standalone":true,"wrap":"none","default-image-extension":"png","html-math-method":{"method":"mathjax","url":"https://cdnjs.cloudflare.com/ajax/libs/mathjax/2.7.0/MathJax.js?config=TeX-AMS_HTML-full"},"slide-level":2,"to":"revealjs","citeproc":true,"filters":["reveal-header","fontawesome"],"embed-resources":true,"output-file":"lecture.slides.html"},"language":{"toc-title-document":"Table of contents","toc-title-website":"On this page","related-formats-title":"Other Formats","related-notebooks-title":"Notebooks","source-notebooks-prefix":"Source","other-links-title":"Other Links","code-links-title":"Code Links","launch-dev-container-title":"Launch Dev Container","launch-binder-title":"Launch Binder","article-notebook-label":"Article Notebook","notebook-preview-download":"Download Notebook","notebook-preview-download-src":"Download Source","notebook-preview-back":"Back to Article","manuscript-meca-bundle":"MECA Bundle","section-title-abstract":"Abstract","section-title-appendices":"Appendices","section-title-footnotes":"Footnotes","section-title-references":"References","section-title-reuse":"Reuse","section-title-copyright":"Copyright","section-title-citation":"Citation","appendix-attribution-cite-as":"For attribution, please cite this work as:","appendix-attribution-bibtex":"BibTeX citation:","title-block-author-single":"Author","title-block-author-plural":"Authors","title-block-affiliation-single":"Affiliation","title-block-affiliation-plural":"Affiliations","title-block-published":"Published","title-block-modified":"Modified","title-block-keywords":"Keywords","callout-tip-title":"Tip","callout-note-title":"Note","callout-warning-title":"Warning","callout-important-title":"Important","callout-caution-title":"Caution","code-summary":"Code","code-tools-menu-caption":"Code","code-tools-show-all-code":"Show All Code","code-tools-hide-all-code":"Hide All Code","code-tools-view-source":"View Source","code-tools-source-code":"Source Code","code-line":"Line","code-lines":"Lines","copy-button-tooltip":"Copy to Clipboard","copy-button-tooltip-success":"Copied!","repo-action-links-edit":"Edit this page","repo-action-links-source":"View source","repo-action-links-issue":"Report an issue","back-to-top":"Back to top","search-no-results-text":"No results","search-matching-documents-text":"matching documents","search-copy-link-title":"Copy link to search","search-hide-matches-text":"Hide additional matches","search-more-match-text":"more match in this document","search-more-matches-text":"more matches in this document","search-clear-button-title":"Clear","search-text-placeholder":"","search-detached-cancel-button-title":"Cancel","search-submit-button-title":"Submit","search-label":"Search","toggle-section":"Toggle section","toggle-sidebar":"Toggle sidebar navigation","toggle-dark-mode":"Toggle dark mode","toggle-reader-mode":"Toggle reader mode","toggle-navigation":"Toggle navigation","crossref-fig-title":"Figure","crossref-tbl-title":"Table","crossref-lst-title":"Listing","crossref-thm-title":"Theorem","crossref-lem-title":"Lemma","crossref-cor-title":"Corollary","crossref-prp-title":"Proposition","crossref-cnj-title":"Conjecture","crossref-def-title":"Definition","crossref-exm-title":"Example","crossref-exr-title":"Exercise","crossref-ch-prefix":"Chapter","crossref-apx-prefix":"Appendix","crossref-sec-prefix":"Section","crossref-eq-prefix":"Equation","crossref-lof-title":"List of Figures","crossref-lot-title":"List of Tables","crossref-lol-title":"List of Listings","environment-proof-title":"Proof","environment-remark-title":"Remark","environment-solution-title":"Solution","listing-page-order-by":"Order By","listing-page-order-by-default":"Default","listing-page-order-by-date-asc":"Oldest","listing-page-order-by-date-desc":"Newest","listing-page-order-by-number-desc":"High to Low","listing-page-order-by-number-asc":"Low to High","listing-page-field-date":"Date","listing-page-field-title":"Title","listing-page-field-description":"Description","listing-page-field-author":"Author","listing-page-field-filename":"File Name","listing-page-field-filemodified":"Modified","listing-page-field-subtitle":"Subtitle","listing-page-field-readingtime":"Reading Time","listing-page-field-wordcount":"Word Count","listing-page-field-categories":"Categories","listing-page-minutes-compact":"{0} min","listing-page-category-all":"All","listing-page-no-matches":"No matching items","listing-page-words":"{0} words"},"metadata":{"lang":"en","fig-responsive":false,"quarto-version":"1.4.533","auto-stretch":true,"modulecode":"PS52007D","bibliography":["../../references.bib","../../textbook.bib"],"csl":"../../apa7.csl","date-format":"long","_quarto-vars":{"author":"Gordon Wright","email":"g.wright@gold.ac.uk","instructor":{"name":"Dr. Gordon Wright","name_no_title":"Gordon Wright","email":"g.wright@gold.ac.uk","url":"www.littlemonkeylab.com","twitter":"drdeception","github":"LittleMonkeyLab","office":"Whitehead 200/1","contact_policy":"E-mail is the best ways to get in contact with me. I will try to respond to all course-related e-mails within 24 hours. Any questions relating to the course, coursework or anything not personal/confidential in nature should be submitted to the Course Forum. This benefits all students. So, if you email me about the course, don't be surprised if you get a brief 'Please post this to the Forum' message!   Office hours are advertised on the module VLE page."},"course":{"number":"PS52007D","semester":"Academic Year 2023-4","days":"Monday Lecture | Tuesday Labs","time":"10am","location":"PSH LG02","dates":"October to March, 2023-4","github":"https://www.github.com/littlemonkeylab/PS52007D_2023-4","url":"https://littlemonkeylab.com/PS52007D_2023-4","copyright_year":"2023"},"university":{"name":"Goldsmiths, University of London","url":"https://www.gold.ac.uk"},"school":{"name":"Department of Psychology","url":"https://gold.ac.uk/psychology"}},"comments":{"hypothesis":{"theme":"clean","openSidebar":false}},"editor":"visual","theme":"../_resources/templates/lectures.scss","mainfont":"Atkinson Hyperlegible","slideNumber":"c/t","menu":true,"controls":true,"navigationMode":"linear","controlsLayout":"edges","showSlideNumber":"all","previewLinks":true,"margin":0.2,"smaller":false,"pdfPageHeightOffset":-2,"max-width":"90%","maxScale":2,"pdfMaxPagesPerSlide":1,"title":"Practical Issues 2023: Deviously Seeking Duping Delight in the Dark","subtitle":"LittleMonkeyLab","image":"lecture.png","author":[{"name":"Dr. Gordon Wright","orcid":"0000-0001-9424-5743","email":"g.wright@gold.ac.uk"}],"date":"10/31/2023","license":"CC BY-NC-SA","citations-hover":true,"categories":["Lecture","Week 21"],"params":{"class":"lec21"},"title-slide-attributes":{"data-background-color":"#BE3455"},"header-logo":"/images/LMLLOGO.png","header":"Practical Issues - Duping Delight","hide-from-titleSlide":"text"}}},"projectFormats":["html","pdf"]}